softpotato/__init__.py
softpotato/technique.py
softpotato-0.0.3.dist-info/LICENSE
softpotato-0.0.3.dist-info/METADATA
softpotato-0.0.3.dist-info/WHEEL
softpotato-0.0.3.dist-info/top_level.txt
softpotato-0.0.3.dist-info/RECORD
