Metadata-Version: 2.1
Name: softpotato
Version: 0.0.3
Summary: First upload to PyPI of Soft Potato scripting version.
Home-page: https://github.com/oliverrdz/softpotato_py
Author: Oliver Rodriguez
Author-email: oliver.rdz@gmail.com
License: UNKNOWN
Project-URL: Bug Tracker, https://github.com/oliverrdz/softpotato_py/issues
Platform: UNKNOWN
Classifier: Programming Language :: Python :: 3
Classifier: License :: OSI Approved :: GNU General Public License v3 (GPLv3)
Classifier: Operating System :: OS Independent
Requires-Python: >3.9
License-File: LICENSE
